pystorz/__init__.py
pystorz/browse/__init__.py
pystorz/browse/server.py
pystorz/browse/templates/__init__.py
pystorz/browse/templates/base.html
pystorz/browse/templates/index.html
pystorz/browse/templates/viewer.html
pystorz/handler/store.py
pystorz/internal/__init__.py
pystorz/internal/constants.py
pystorz/memory/memory.py
pystorz/meta/__init__.py
pystorz/meta/store.py
pystorz/mgen/__init__.py
pystorz/mgen/generator.py
pystorz/mgen/meta.py
pystorz/mgen/test.py
pystorz/mgen/utils.py
pystorz/mgen/templates/__init__.py
pystorz/mgen/templates/javascript.js
pystorz/mgen/templates/openapi.xml
pystorz/mgen/templates/python.py
pystorz/mgen/templates/python.template
pystorz/mongo/mongo.py
pystorz/rest/__init__.py
pystorz/rest/client.py
pystorz/rest/headers.py
pystorz/rest/internals.py
pystorz/rest/server.py
pystorz/router/__init__.py
pystorz/router/store.py
pystorz/sql/__init__.py
pystorz/sql/adapter.py
pystorz/sql/mysql.py
pystorz/sql/sqlite.py
pystorz/sql/store.py
pystorz/store/__init__.py
pystorz/store/options.py
pystorz/store/store.py
pystorz/store/utils.py
pystorz-0.7.12.dist-info/LICENSE
pystorz-0.7.12.dist-info/METADATA
pystorz-0.7.12.dist-info/WHEEL
pystorz-0.7.12.dist-info/top_level.txt
pystorz-0.7.12.dist-info/RECORD
