Metadata-Version: 2.1
Name: pystorz
Version: 0.7.12
Summary: Python package for the Storz object store framework.
Home-page: https://github.com/wazofski/pystorz
Author: wazofski
Classifier: Intended Audience :: Developers
Classifier: Programming Language :: Python :: 3.7
Requires-Python: >=3.6
License-File: LICENSE
Requires-Dist: PyYAML
Requires-Dist: jinja2
Requires-Dist: black
Requires-Dist: jsonpath-python
Requires-Dist: cherrypy
Requires-Dist: requests
Requires-Dist: mysql-connector-python
Requires-Dist: sqlparse
Requires-Dist: pymongo
Requires-Dist: flask
Provides-Extra: dev
